teletype/__init__.py
teletype/__main__.py
teletype/__version__.py
teletype/components.py
teletype/py.typed
teletype/typedef.py
teletype/codes/__init__.py
teletype/codes/common.py
teletype/codes/posix.py
teletype/codes/windows.py
teletype/io/__init__.py
teletype/io/common.py
teletype/io/posix.py
teletype/io/windows.py
teletype-1.3.4.dist-info/LICENSE.txt
teletype-1.3.4.dist-info/METADATA
teletype-1.3.4.dist-info/WHEEL
teletype-1.3.4.dist-info/top_level.txt
teletype-1.3.4.dist-info/zip-safe
teletype-1.3.4.dist-info/RECORD
